py_wsi/__init__.py
py_wsi/dataset.py
py_wsi/imagepy_toolkit.py
py_wsi/item.py
py_wsi/patch_reader.py
py_wsi/store.py
py_wsi/turtle.py
py_wsi-1.0.dist-info/METADATA
py_wsi-1.0.dist-info/RECORD
py_wsi-1.0.dist-info/WHEEL
py_wsi-1.0.dist-info/top_level.txt
