Metadata-Version: 2.1
Name: py-wsi
Version: 1.0
Summary: Python package for dealing with whole slide images (.svs) for machine learning, including
Home-page: https://github.com/ysbecca/py-wsi
Author: Rebecca Stone
Author-email: ysbecca@gmail.com
License: GNU General Public License v3.0
Keywords: whole slide images svs openslide lmdb machine learning
Platform: UNKNOWN
Requires-Dist: shapely
Requires-Dist: numpy
Requires-Dist: openslide-python
Requires-Dist: lmdb
Requires-Dist: Pillow
